cargo_vcs.py
cargo_vcs-2.4.dist-info/METADATA
cargo_vcs-2.4.dist-info/WHEEL
cargo_vcs-2.4.dist-info/entry_points.txt
cargo_vcs-2.4.dist-info/top_level.txt
cargo_vcs-2.4.dist-info/RECORD
